ckanext_datajson-0.1.28-nspkg.pth
ckanext/datajson/blueprint.py
ckanext/datajson/datajson.py
ckanext/datajson/datajsonvalidator.py
ckanext/datajson/exceptions.py
ckanext/datajson/harvester_base.py
ckanext/datajson/harvester_cmsdatanavigator.py
ckanext/datajson/harvester_datajson.py
ckanext/datajson/helpers.py
ckanext/datajson/package2pod.py
ckanext/datajson/parse_datajson.py
ckanext/datajson/plugin.py
ckanext/datajson/export_map/export.catalog.map.sample.json
ckanext/datajson/export_map/export.inventory.map.sample.json
ckanext/datajson/export_map/export.spatial.map.sample.json
ckanext/datajson/pod_schema/single_entry.json
ckanext/datajson/pod_schema/federal-v1.1/catalog.json
ckanext/datajson/pod_schema/federal-v1.1/dataset.json
ckanext/datajson/pod_schema/non-federal/single_entry.json
ckanext/datajson/pod_schema/non-federal-v1.1/catalog.json
ckanext/datajson/pod_schema/non-federal-v1.1/dataset-non-federal.json
ckanext/datajson/resources/additional_resource_formats.json
ckanext/datajson/resources/harvest-to-program-codes.json
ckanext/datajson/resources/omb-agency-bureau-treasury-codes.json
ckanext/datajson/resources/omb_bureau_codes.csv
ckanext/datajson/templates_datajson/organization/read.html
ckanext/datajson/templates_validator/datajsonvalidator.html
ckanext/datajson/tests/__init__.py
ckanext/datajson/tests/factories.py
ckanext/datajson/tests/mock_datajson_source.py
ckanext/datajson/tests/test_collections_ui.py
ckanext/datajson/tests/test_datajson_ckan_all_harvester.py
ckanext/datajson/tests/test_datajson_validation.py
ckanext/datajson/tests/test_export.py
ckanext_datajson-0.1.28.dist-info/LICENSE.md
ckanext_datajson-0.1.28.dist-info/METADATA
ckanext_datajson-0.1.28.dist-info/WHEEL
ckanext_datajson-0.1.28.dist-info/entry_points.txt
ckanext_datajson-0.1.28.dist-info/namespace_packages.txt
ckanext_datajson-0.1.28.dist-info/top_level.txt
ckanext_datajson-0.1.28.dist-info/RECORD
