Metadata-Version: 2.1
Name: ckanext-datajson
Version: 0.1.28
Summary: CKAN extension to generate /data.json
Home-page: https://github.com/GSA/ckanext-datajson
Author: Data.gov
Author-email: datagovhelp@gsa.gov
License: Public Domain
Classifier: Programming Language :: Python :: 3
License-File: LICENSE.md
Requires-Dist: jsonschema ~=2.4.0
Requires-Dist: pyyaml
Requires-Dist: rfc3987
Requires-Dist: sansjson ==0.3.0
